arnavArithmetic/__init__.py
arnavArithmetic/add.py
arnavArithmetic/div.py
arnavArithmetic/mul.py
arnavArithmetic/sub.py
arnavArithmetic-0.0.1.dist-info/LICENSE
arnavArithmetic-0.0.1.dist-info/METADATA
arnavArithmetic-0.0.1.dist-info/WHEEL
arnavArithmetic-0.0.1.dist-info/top_level.txt
arnavArithmetic-0.0.1.dist-info/RECORD
